test/__init__.py
test/test_passport_data.py
test/test_visa_status.py
visa_cli/__init__.py
visa_cli/visa_status.py
visa_cli/passport_data/__init__.py
visa_cli/passport_data/passport_data.py
visa_cli-0.2.1.dist-info/LICENSE
visa_cli-0.2.1.dist-info/METADATA
visa_cli-0.2.1.dist-info/WHEEL
visa_cli-0.2.1.dist-info/entry_points.txt
visa_cli-0.2.1.dist-info/top_level.txt
visa_cli-0.2.1.dist-info/RECORD
