Metadata-Version: 2.1
Name: visa-cli
Version: 0.2.1
Summary: CLI tool to lookup Visa status for Countries
Home-page: https://github.com/rand-net/visa-cli
Author: rand-net
License: MIT
Keywords: awesome list,awesome,resources,lists,mammoths
Platform: UNKNOWN
Classifier: License :: OSI Approved :: MIT License
Classifier: Programming Language :: Python :: 3
Classifier: Programming Language :: Python :: 3.8
License-File: LICENSE
Requires-Dist: art
Requires-Dist: prompt-toolkit
Requires-Dist: requests
Requires-Dist: pandas
Requires-Dist: tabulate
